japanera/__about__.py
japanera/__init__.py
japanera/era_data.py
japanera/japanera.py
japanera/parser.py
japanera-2.1.3.dist-info/METADATA
japanera-2.1.3.dist-info/WHEEL
japanera-2.1.3.dist-info/licenses/LICENSE
japanera-2.1.3.dist-info/RECORD
