Metadata-Version: 2.4
Name: japanera
Version: 2.1.3
Summary: Easy japanese era tool
Project-URL: Homepage, https://github.com/nagataaaas/Japanera
Project-URL: Documentation, https://github.com/nagataaaas/Japanera/blob/master/README.md
Project-URL: Repository, https://github.com/nagataaaas/Japanera.git
Project-URL: Issues, https://github.com/nagataaaas/Japanera/issues
Project-URL: Changelog, https://github.com/nagataaaas/Japanera/blob/master/CHANGELOG.md
Author-email: nagataaaas <nagata@nagata.pro>
License-File: LICENSE
Keywords: calendar,conversion,date,era,japanese,kanji
Classifier: Development Status :: 4 - Beta
Classifier: Environment :: Other Environment
Classifier: Intended Audience :: Developers
Classifier: License :: OSI Approved :: MIT License
Classifier: Operating System :: OS Independent
Classifier: Programming Language :: Python
Classifier: Programming Language :: Python :: 3
Classifier: Topic :: Software Development :: Libraries :: Python Modules
Requires-Python: >=3.8
Requires-Dist: kanjize>=1.6.1
